{
    "version": "3.9.5.0",
    "description": "ACT 国服整合，自带超方便插件中心的 Advanced Combat Tracker 整合版。",
    "homepage": "https://ffcafe.org/act/",
    "license": {
        "identifier": "Freeware"
    },
    "url": "https://cafemenu-dl.xivcdn.com/act/update/download/3.9.5.0_sfx.exe#/dl.7z",
    "hash": "3daa872e45d7de7149376e84154c19d32765d758f72ad230c50a3262cf575be7",
    "shortcuts": [
        [
            "CafeACT.exe",
            "CafeACT"
        ]
    ],
    "persist": [
        "AppData",
        "Backup",
        "Dpshow",
        "Plugins",
        "Temp"
    ],
    "checkver": {
        "script": "(Invoke-WebRequest -Uri 'https://cafemenu.lv5.one/act/update/download?channel=release&variant=sfx&version=latest' -MaximumRedirection 0 -SkipHttpErrorCheck -ErrorAction:SilentlyContinue).Headers.Location",
        "regex": "([\\d.]+)_sfx\\.exe"
    },
    "autoupdate": {
        "url": "https://cafemenu-dl.xivcdn.com/act/update/download/$version_sfx.exe#/dl.7z"
    }
}
